Workbook

Sheet 0_Dashboard
A1: Market Dashboard（美股读盘框架）
A2: 把宏观流动性 × 微观基本面 × 价格行动落地为“可每周更新”的评分体系。
A5: 模块 | B5: 指标 | C5: 当前值(链接/输入) | D5: 环比 | E5: 阈值/规则 | F5: 状态(公式) | G5: 得分(公式) | H5: 注释
A6: 流动性 | B6: 宏观政策得分(合计) | C6: ='1_Macro_Liquidity'!H11 -> 0 | E6: >=2宽松; 0-1中性; <0收紧 | F6: =IF(C6="","",IF(C6>=2,"宽松",IF(C6>=0,"中性","收紧"))) -> 中性 | G6: =IF(C6="","",IF(C6>=2,1,IF(C6>=0,0,-1))) -> 0 | H6: 点阵图/中性利率/分歧/不确定性
A7: 流动性 | B7: 实际利率得分(最近) | C7: ='2_RealRate_Valuation'!B37 | E7: 10Y TIPS <=0.75→+1 | F7: =IF(C7="","",IF(C7=1,"宽松",IF(C7=0,"中性","收紧"))) | G7: =C7 | H7: 实际利率下行利好成长
A8: 流动性 | B8: TGA得分(最近) | C8: =IFERROR(LOOKUP(2,1/('3_TGA_RRP'!F6:F35<>""),'3_TGA_RRP'!F6:F35),"") | E8: TGA<8500→+1 | F8: =IF(C8="","",IF(C8=1,"释放",IF(C8=0,"中性","收缩"))) | G8: =C8 | H8: TGA下降=释放流动性
A9: 基本面 | B9: Mag7得分(加权) | C9: ='4_Micro_Fundamentals'!G25 -> 1.0003 | E9: >=0.3强; 0-0.29中; <0弱 | F9: =IF(C9="","",IF(C9>=0.3,"强",IF(C9>=0,"中","弱"))) -> 强 | G9: =IF(C9="","",IF(C9>=0.3,1,IF(C9>=0,0,-1))) -> 1 | H9: 超预期+利润率+FCF
A10: 情绪 | B10: 利好不涨比例 | C10: ='5_Price_Action'!B89 -> 0 | E10: <30%健康; 30-45%警惕; >45%风险 | F10: =IF(C10="","",IF(C10<0.3,"健康",IF(C10<0.45,"警惕","风险"))) -> 健康 | G10: =IF(C10="","",IF(C10<0.3,1,IF(C10<0.45,0,-1))) -> 1 | H10: Good news, bad reaction
A11: 情绪 | B11: 利空不跌比例 | C11: ='5_Price_Action'!B90 -> 0 | E11: >25%偏底部; <10%偏顶部 | F11: =IF(C11="","",IF(C11>0.25,"偏底部",IF(C11>0.1,"中性","偏顶部"))) -> 偏顶部 | G11: =IF(C11="","",IF(C11>0.25,1,IF(C11>0.1,0,-1))) -> -1 | H11: Bad news, good reaction
A12: 广度 | B12: 板块联动均值 | C12: ='5_Price_Action'!B91 | E12: >0.60广度好; 0.4-0.6一般; <0.4差 | F12: =IF(C12="","",IF(C12>0.6,"良好",IF(C12>0.4,"一般","较差"))) | G12: =IF(C12="","",IF(C12>0.6,1,IF(C12>0.4,0,-1))) | H12: 龙头带动板块
A14: 总分（-6 到 +6） | B14: =SUM(G6:G12) -> 1
A15: 流动性总分 | B15: =SUM(G6:G8) -> 0
A16: 业绩/基本面得分 | B16: =G9 -> 1
A17: 市场状态（矩阵输出） | B17: =_xlfn.LET(_xlpm.liq,B15,_xlpm.fund,B16,_xlpm.liqState,IF(_xlpm.liq>=2,"宽松",IF(_xlpm.liq<=0,"收紧","中性")),IF(AND(_xlpm.liqState="宽松",_xlpm.fund=1),"主升浪",IF(AND(_xlpm.liqState="宽松",_xlpm.fund<=0),"震荡",IF(AND(_xlpm.liqState="收紧",_xlpm.fund=1),"分化","双杀")))) -> 分化
A19: 使用说明（快速）
A20: 1) 先在 Sheet1/2/3 填宏观与流动性；2) Sheet4 填Mag7财报核心数字；3) Sheet5 记录“利好不涨/利空不跌”；4) 回到本页看总分与市场状态。

Sheet 1_Macro_Liquidity
A1: 宏观流动性（美联储与点阵图）
A2: 输入每次FOMC更新后的关键数字；用“评分”给宏观方向打分（+1/0/-1）。
A3: 更新日期（本行） | B3: 2026-02-10
A5: 指标 | B5: 最新值(输入) | C5: 上次值(输入) | D5: 变化(公式) | E5: 阈值/参考(输入) | F5: 评分(公式) | G5: 解读/备注 | H5: 数据来源(可选)
A6: 2026年末点阵图中值(%) | D6: =IF(OR(B6="",C6=""),"",B6-C6) | E6: 下降→偏鸽 | F6: =IF(B6="","",IF(D6<0,1,IF(D6>0,-1,0))) | G6: 关注“降到哪”而非“降多少”
A7: 长期中性利率(%) | D7: =IF(OR(B7="",C7=""),"",B7-C7) | E7: 锚点 | F7: =IF(B7="","",IF(D7>0,-1,IF(D7<0,1,0))) | G7: 中性利率若上修→估值中枢下移风险
A8: 预计不降息官员数 | D8: =IF(OR(B8="",C8=""),"",B8-C8) | E8: 分歧 | F8: =IF(B8="","",IF(D8>0,-1,IF(D8<0,1,0))) | G8: 人数上升→政策不确定性↑
A9: 主席更替/政策不确定性(0-2) | D9: =IF(OR(B9="",C9=""),"",B9-C9) | E9: 0低 1中 2高 | F9: =IF(B9="","",IF(B9>=2,-1,IF(B9=1,0,1))) | G9: 换届年可上调风险折价
G11: 宏观政策得分（合计） | H11: =SUM(F6:F9) -> 0

Sheet 2_RealRate_Valuation
A1: 实际利率与估值（Real Rate）
A2: 输入10Y TIPS（实际利率）与指数表现，用阈值判断成长股估值环境。
A3: 监控区间：0.50%–0.75%（适度限制性）
A5: 日期 | B5: 10Y TIPS(%) 输入 | C5: 1M前 输入 | D5: 变化(公式) | E5: 阈值上限(%) 输入 | F5: 评分(公式) | G5: 备注 | H5: 来源
D6: =IF(OR(B6="",C6=""),"",B6-C6) | E6: 0.75 | F6: =IF(B6="","",IF(B6<=E6,1,IF(B6<=E6+0.25,0,-1)))
D7: =IF(OR(B7="",C7=""),"",B7-C7) | E7: 0.75 | F7: =IF(B7="","",IF(B7<=E7,1,IF(B7<=E7+0.25,0,-1)))
D8: =IF(OR(B8="",C8=""),"",B8-C8) | E8: 0.75 | F8: =IF(B8="","",IF(B8<=E8,1,IF(B8<=E8+0.25,0,-1)))
D9: =IF(OR(B9="",C9=""),"",B9-C9) | E9: 0.75 | F9: =IF(B9="","",IF(B9<=E9,1,IF(B9<=E9+0.25,0,-1)))
D10: =IF(OR(B10="",C10=""),"",B10-C10) | E10: 0.75 | F10: =IF(B10="","",IF(B10<=E10,1,IF(B10<=E10+0.25,0,-1)))
D11: =IF(OR(B11="",C11=""),"",B11-C11) | E11: 0.75 | F11: =IF(B11="","",IF(B11<=E11,1,IF(B11<=E11+0.25,0,-1)))
D12: =IF(OR(B12="",C12=""),"",B12-C12) | E12: 0.75 | F12: =IF(B12="","",IF(B12<=E12,1,IF(B12<=E12+0.25,0,-1)))
D13: =IF(OR(B13="",C13=""),"",B13-C13) | E13: 0.75 | F13: =IF(B13="","",IF(B13<=E13,1,IF(B13<=E13+0.25,0,-1)))
D14: =IF(OR(B14="",C14=""),"",B14-C14) | E14: 0.75 | F14: =IF(B14="","",IF(B14<=E14,1,IF(B14<=E14+0.25,0,-1)))
D15: =IF(OR(B15="",C15=""),"",B15-C15) | E15: 0.75 | F15: =IF(B15="","",IF(B15<=E15,1,IF(B15<=E15+0.25,0,-1)))
D16: =IF(OR(B16="",C16=""),"",B16-C16) | E16: 0.75 | F16: =IF(B16="","",IF(B16<=E16,1,IF(B16<=E16+0.25,0,-1)))
D17: =IF(OR(B17="",C17=""),"",B17-C17) | E17: 0.75 | F17: =IF(B17="","",IF(B17<=E17,1,IF(B17<=E17+0.25,0,-1)))
... D35: =IF(OR(B35="",C35=""),"",B35-C35) | E35: 0.75 | F35: =IF(B35="","",IF(B35<=E35,1,IF(B35<=E35+0.25,0,-1)))
A37: 实际利率得分（最近一行） | B37: =IFERROR(LOOKUP(2,1/(F6:F35<>""),F6:F35),"")

Sheet 3_TGA_RRP
A1: TGA 与 RRP（财政流动性）
A2: TGA下降=释放流动性；RRP见底时“弹性”通常更大。
A5: 日期 | B5: TGA(亿美元) 输入 | C5: 上期TGA 输入 | D5: TGA变化(公式) | E5: 目标余额(亿美元) 输入 | F5: 评分(公式) | G5: 备注 | H5: 来源
D6: =IF(OR(B6="",C6=""),"",B6-C6) | E6: 8500 | F6: =IF(B6="","",IF(B6<=E6,1,IF(B6<=E6+300,0,-1)))
D7: =IF(OR(B7="",C7=""),"",B7-C7) | E7: 8500 | F7: =IF(B7="","",IF(B7<=E7,1,IF(B7<=E7+300,0,-1)))
D8: =IF(OR(B8="",C8=""),"",B8-C8) | E8: 8500 | F8: =IF(B8="","",IF(B8<=E8,1,IF(B8<=E8+300,0,-1)))
D9: =IF(OR(B9="",C9=""),"",B9-C9) | E9: 8500 | F9: =IF(B9="","",IF(B9<=E9,1,IF(B9<=E9+300,0,-1)))
D10: =IF(OR(B10="",C10=""),"",B10-C10) | E10: 8500 | F10: =IF(B10="","",IF(B10<=E10,1,IF(B10<=E10+300,0,-1)))
D11: =IF(OR(B11="",C11=""),"",B11-C11) | E11: 8500 | F11: =IF(B11="","",IF(B11<=E11,1,IF(B11<=E11+300,0,-1)))
D12: =IF(OR(B12="",C12=""),"",B12-C12) | E12: 8500 | F12: =IF(B12="","",IF(B12<=E12,1,IF(B12<=E12+300,0,-1)))
D13: =IF(OR(B13="",C13=""),"",B13-C13) | E13: 8500 | F13: =IF(B13="","",IF(B13<=E13,1,IF(B13<=E13+300,0,-1)))
D14: =IF(OR(B14="",C14=""),"",B14-C14) | E14: 8500 | F14: =IF(B14="","",IF(B14<=E14,1,IF(B14<=E14+300,0,-1)))
D15: =IF(OR(B15="",C15=""),"",B15-C15) | E15: 8500 | F15: =IF(B15="","",IF(B15<=E15,1,IF(B15<=E15+300,0,-1)))
D16: =IF(OR(B16="",C16=""),"",B16-C16) | E16: 8500 | F16: =IF(B16="","",IF(B16<=E16,1,IF(B16<=E16+300,0,-1)))
D17: =IF(OR(B17="",C17=""),"",B17-C17) | E17: 8500 | F17: =IF(B17="","",IF(B17<=E17,1,IF(B17<=E17+300,0,-1)))
... D35: =IF(OR(B35="",C35=""),"",B35-C35) | E35: 8500 | F35: =IF(B35="","",IF(B35<=E35,1,IF(B35<=E35+300,0,-1)))
A37: RRP监控（可选）
A38: 日期 | B38: RRP(亿美元) 输入 | C38: 上期RRP 输入 | D38: RRP变化(公式) | E38: “见底”阈值(亿美元) 输入 | F38: 评分(公式) | G38: 备注 | H38: 来源
D39: =IF(OR(B39="",C39=""),"",B39-C39) | E39: 1000 | F39: =IF(B39="","",IF(B39<=E39,1,0))
D40: =IF(OR(B40="",C40=""),"",B40-C40) | E40: 1000 | F40: =IF(B40="","",IF(B40<=E40,1,0))
D41: =IF(OR(B41="",C41=""),"",B41-C41) | E41: 1000 | F41: =IF(B41="","",IF(B41<=E41,1,0))
D42: =IF(OR(B42="",C42=""),"",B42-C42) | E42: 1000 | F42: =IF(B42="","",IF(B42<=E42,1,0))
D43: =IF(OR(B43="",C43=""),"",B43-C43) | E43: 1000 | F43: =IF(B43="","",IF(B43<=E43,1,0))
D44: =IF(OR(B44="",C44=""),"",B44-C44) | E44: 1000 | F44: =IF(B44="","",IF(B44<=E44,1,0))
D45: =IF(OR(B45="",C45=""),"",B45-C45) | E45: 1000 | F45: =IF(B45="","",IF(B45<=E45,1,0))
D46: =IF(OR(B46="",C46=""),"",B46-C46) | E46: 1000 | F46: =IF(B46="","",IF(B46<=E46,1,0))
D47: =IF(OR(B47="",C47=""),"",B47-C47) | E47: 1000 | F47: =IF(B47="","",IF(B47<=E47,1,0))
D48: =IF(OR(B48="",C48=""),"",B48-C48) | E48: 1000 | F48: =IF(B48="","",IF(B48<=E48,1,0))
D49: =IF(OR(B49="",C49=""),"",B49-C49) | E49: 1000 | F49: =IF(B49="","",IF(B49<=E49,1,0))
D50: =IF(OR(B50="",C50=""),"",B50-C50) | E50: 1000 | F50: =IF(B50="","",IF(B50<=E50,1,0))
... D58: =IF(OR(B58="",C58=""),"",B58-C58) | E58: 1000 | F58: =IF(B58="","",IF(B58<=E58,1,0))

Sheet 4_Micro_Fundamentals
A1: 微观基本面（Mag 7）
A2: 每季财报后更新：EPS增速、AI占比、CapEx强度、利润率、FCF。用红线规则识别风险。
A3: 提示：成本增速 > 营收增速通常触发“杀估值”；利润率( Margin )指引更关键。
A5: Ticker | B5: 公司 | C5: EPS YoY(%) 输入 | D5: 预期EPS(%) 输入 | E5: Surprise(公式) | F5: AI收入占比(%) 输入 | G5: CapEx/Rev(%) 输入 | H5: Margin QoQ(pp) 输入 | I5: FCF YoY(%) 输入
A6: AAPL | B6: Apple | E6: =IF(OR(C6="",D6=""),"",C6-D6)
A7: MSFT | B7: Microsoft | E7: =IF(OR(C7="",D7=""),"",C7-D7)
A8: NVDA | B8: NVIDIA | E8: =IF(OR(C8="",D8=""),"",C8-D8)
A9: GOOGL | B9: Alphabet | E9: =IF(OR(C9="",D9=""),"",C9-D9)
A10: AMZN | B10: Amazon | E10: =IF(OR(C10="",D10=""),"",C10-D10)
A11: META | B11: Meta | E11: =IF(OR(C11="",D11=""),"",C11-D11)
A12: TSLA | B12: Tesla | E12: =IF(OR(C12="",D12=""),"",C12-D12)
A15: Mag7综合得分（按“超预期+利润率+FCF”粗略打分，可自行改权重）
A16: Ticker | B16: Surprise | C16: Margin QoQ | D16: FCF YoY | E16: 单股得分(公式) | F16: 权重(输入) | G16: 加权得分(公式) | H16: 备注
A17: AAPL | B17: =E6 | C17: =H6 | D17: =I6 | E17: =IFERROR(SIGN((IF(B17>0,1,0)+IF(C17>0,1,0)+IF(D17>0,1,0))-1),"") -> 1 | F17: 0.1429 | G17: =IF(OR(E17="",F17=""),"",E17*F17) -> 0.1429
A18: MSFT | B18: =E7 | C18: =H7 | D18: =I7 | E18: =IFERROR(SIGN((IF(B18>0,1,0)+IF(C18>0,1,0)+IF(D18>0,1,0))-1),"") -> 1 | F18: 0.1429 | G18: =IF(OR(E18="",F18=""),"",E18*F18) -> 0.1429
A19: NVDA | B19: =E8 | C19: =H8 | D19: =I8 | E19: =IFERROR(SIGN((IF(B19>0,1,0)+IF(C19>0,1,0)+IF(D19>0,1,0))-1),"") -> 1 | F19: 0.1429 | G19: =IF(OR(E19="",F19=""),"",E19*F19) -> 0.1429
A20: GOOGL | B20: =E9 | C20: =H9 | D20: =I9 | E20: =IFERROR(SIGN((IF(B20>0,1,0)+IF(C20>0,1,0)+IF(D20>0,1,0))-1),"") -> 1 | F20: 0.1429 | G20: =IF(OR(E20="",F20=""),"",E20*F20) -> 0.1429
A21: AMZN | B21: =E10 | C21: =H10 | D21: =I10 | E21: =IFERROR(SIGN((IF(B21>0,1,0)+IF(C21>0,1,0)+IF(D21>0,1,0))-1),"") -> 1 | F21: 0.1429 | G21: =IF(OR(E21="",F21=""),"",E21*F21) -> 0.1429
A22: META | B22: =E11 | C22: =H11 | D22: =I11 | E22: =IFERROR(SIGN((IF(B22>0,1,0)+IF(C22>0,1,0)+IF(D22>0,1,0))-1),"") -> 1 | F22: 0.1429 | G22: =IF(OR(E22="",F22=""),"",E22*F22) -> 0.1429
A23: TSLA | B23: =E12 | C23: =H12 | D23: =I12 | E23: =IFERROR(SIGN((IF(B23>0,1,0)+IF(C23>0,1,0)+IF(D23>0,1,0))-1),"") -> 1 | F23: 0.1429 | G23: =IF(OR(E23="",F23=""),"",E23*F23) -> 0.1429
F24: 权重合计 | G24: =SUM(F17:F23) -> 0
F25: Mag7得分（加权） | G25: =SUM(G17:G23) -> 1.0003

Sheet 5_Price_Action
A1: 价格行动（财报后反应）
A2: 记录“利好不涨 / 利空不跌”频率与板块联动性，用作牛熊转换最敏感信号。
A5: 日期 | B5: Ticker | C5: EPS结果 | D5: 指引结果 | E5: 开盘反应 | F5: 收盘反应 | G5: 类型(公式) | H5: 板块联动(0-1) 输入 | I5: 备注
G6: =IF(OR(C6="",F6=""),"",IF(AND(OR(C6="Beat",D6="上修"),OR(F6="回落",F6="收跌")),"利好不涨",IF(AND(OR(C6="Miss",D6="下修"),OR(F6="反弹",F6="震荡")),"利空不跌","正常")))
G7: =IF(OR(C7="",F7=""),"",IF(AND(OR(C7="Beat",D7="上修"),OR(F7="回落",F7="收跌")),"利好不涨",IF(AND(OR(C7="Miss",D7="下修"),OR(F7="反弹",F7="震荡")),"利空不跌","正常")))
G8: =IF(OR(C8="",F8=""),"",IF(AND(OR(C8="Beat",D8="上修"),OR(F8="回落",F8="收跌")),"利好不涨",IF(AND(OR(C8="Miss",D8="下修"),OR(F8="反弹",F8="震荡")),"利空不跌","正常")))
G9: =IF(OR(C9="",F9=""),"",IF(AND(OR(C9="Beat",D9="上修"),OR(F9="回落",F9="收跌")),"利好不涨",IF(AND(OR(C9="Miss",D9="下修"),OR(F9="反弹",F9="震荡")),"利空不跌","正常")))
G10: =IF(OR(C10="",F10=""),"",IF(AND(OR(C10="Beat",D10="上修"),OR(F10="回落",F10="收跌")),"利好不涨",IF(AND(OR(C10="Miss",D10="下修"),OR(F10="反弹",F10="震荡")),"利空不跌","正常")))
G11: =IF(OR(C11="",F11=""),"",IF(AND(OR(C11="Beat",D11="上修"),OR(F11="回落",F11="收跌")),"利好不涨",IF(AND(OR(C11="Miss",D11="下修"),OR(F11="反弹",F11="震荡")),"利空不跌","正常")))
G12: =IF(OR(C12="",F12=""),"",IF(AND(OR(C12="Beat",D12="上修"),OR(F12="回落",F12="收跌")),"利好不涨",IF(AND(OR(C12="Miss",D12="下修"),OR(F12="反弹",F12="震荡")),"利空不跌","正常")))
G13: =IF(OR(C13="",F13=""),"",IF(AND(OR(C13="Beat",D13="上修"),OR(F13="回落",F13="收跌")),"利好不涨",IF(AND(OR(C13="Miss",D13="下修"),OR(F13="反弹",F13="震荡")),"利空不跌","正常")))
G14: =IF(OR(C14="",F14=""),"",IF(AND(OR(C14="Beat",D14="上修"),OR(F14="回落",F14="收跌")),"利好不涨",IF(AND(OR(C14="Miss",D14="下修"),OR(F14="反弹",F14="震荡")),"利空不跌","正常")))
G15: =IF(OR(C15="",F15=""),"",IF(AND(OR(C15="Beat",D15="上修"),OR(F15="回落",F15="收跌")),"利好不涨",IF(AND(OR(C15="Miss",D15="下修"),OR(F15="反弹",F15="震荡")),"利空不跌","正常")))
G16: =IF(OR(C16="",F16=""),"",IF(AND(OR(C16="Beat",D16="上修"),OR(F16="回落",F16="收跌")),"利好不涨",IF(AND(OR(C16="Miss",D16="下修"),OR(F16="反弹",F16="震荡")),"利空不跌","正常")))
G17: =IF(OR(C17="",F17=""),"",IF(AND(OR(C17="Beat",D17="上修"),OR(F17="回落",F17="收跌")),"利好不涨",IF(AND(OR(C17="Miss",D17="下修"),OR(F17="反弹",F17="震荡")),"利空不跌","正常")))
... G85: =IF(OR(C85="",F85=""),"",IF(AND(OR(C85="Beat",D85="上修"),OR(F85="回落",F85="收跌")),"利好不涨",IF(AND(OR(C85="Miss",D85="下修"),OR(F85="反弹",F85="震荡")),"利空不跌","正常")))
A88: 统计（最近80条记录）
A89: 利好不涨比例 | B89: =IFERROR(COUNTIF(G6:G85,"利好不涨")/COUNTIF(G6:G85,"<>"),"") -> 0
A90: 利空不跌比例 | B90: =IFERROR(COUNTIF(G6:G85,"利空不跌")/COUNTIF(G6:G85,"<>"),"") -> 0
A91: 板块联动均值 | B91: =IFERROR(AVERAGEIF(H6:H85,">=0"),"")
