Workbook

Sheet 0_Dashboard
A1: Market Dashboard（美股读盘框架）
A2: 把宏观流动性 × 微观基本面 × 价格行动落地为“可每周更新”的评分体系。
A5: 模块 | B5: 指标 | C5: 当前值(链接/输入) | D5: 环比 | E5: 阈值/规则 | F5: 状态(公式) | G5: 得分(公式) | H5: 注释
A6: 流动性 | B6: 宏观政策得分(合计) | C6: ='1_Macro_Liquidity'!H11 | E6: >=2宽松; 0-1中性; <0收紧 | F6: =IF(C6="","",IF(C6>=2,"宽松",IF(C6>=0,"中性","收紧"))) | G6: =IF(C6="","",IF(C6>=2,1,IF(C6>=0,0,-1))) | H6: 点阵图/中性利率/分歧/不确定性
A7: 流动性 | B7: 实际利率得分(最近) | C7: ='2_RealRate_Valuation'!B37 | E7: 10Y TIPS <=0.75→+1 | F7: =IF(C7="","",IF(C7=1,"宽松",IF(C7=0,"中性","收紧"))) | G7: =C7 | H7: 实际利率下行利好成长
A8: 流动性 | B8: TGA得分(最近) | C8: =IFERROR(LOOKUP(2,1/('3_TGA_RRP'!F6:F35<>""),'3_TGA_RRP'!F6:F35),"") | E8: TGA<8500→+1 | F8: =IF(C8="","",IF(C8=1,"释放",IF(C8=0,"中性","收缩"))) | G8: =C8 | H8: TGA下降=释放流动性
A9: 基本面 | B9: Mag7得分(加权) | C9: ='4_Micro_Fundamentals'!G25 | E9: >=0.3强; 0-0.29中; <0弱 | F9: =IF(C9="","",IF(C9>=0.3,"强",IF(C9>=0,"中","弱"))) | G9: =IF(C9="","",IF(C9>=0.3,1,IF(C9>=0,0,-1))) | H9: 超预期+利润率+FCF
A10: 情绪 | B10: 利好不涨比例 | C10: ='5_Price_Action'!B89 | E10: <30%健康; 30-45%警惕; >45%风险 | F10: =IF(C10="","",IF(C10<0.3,"健康",IF(C10<0.45,"警惕","风险"))) | G10: =IF(C10="","",IF(C10<0.3,1,IF(C10<0.45,0,-1))) | H10: Good news, bad reaction
A11: 情绪 | B11: 利空不跌比例 | C11: ='5_Price_Action'!B90 | E11: >25%偏底部; <10%偏顶部 | F11: =IF(C11="","",IF(C11>0.25,"偏底部",IF(C11>0.1,"中性","偏顶部"))) | G11: =IF(C11="","",IF(C11>0.25,1,IF(C11>0.1,0,-1))) | H11: Bad news, good reaction
A12: 广度 | B12: 板块联动均值 | C12: ='5_Price_Action'!B91 | E12: >0.60广度好; 0.4-0.6一般; <0.4差 | F12: =IF(C12="","",IF(C12>0.6,"良好",IF(C12>0.4,"一般","较差"))) | G12: =IF(C12="","",IF(C12>0.6,1,IF(C12>0.4,0,-1))) | H12: 龙头带动板块
A14: 总分（-6 到 +6） | B14: =SUM(G6:G12)
A15: 流动性总分 | B15: =SUM(G6:G8)
A16: 业绩/基本面得分 | B16: =G9
A17: 市场状态（矩阵输出） | B17: =LET(liq,B15,fund,B16,liqState,IF(liq>=2,"宽松",IF(liq<=0,"收紧","中性")),IF(AND(liqState="宽松",fund=1),"主升浪",IF(AND(liqState="宽松",fund<=0),"震荡",IF(AND(liqState="收紧",fund=1),"分化","双杀"))))
A19: 使用说明（快速）
A20: 1) 先在 Sheet1/2/3 填宏观与流动性；2) Sheet4 填Mag7财报核心数字；3) Sheet5 记录“利好不涨/利空不跌”；4) 回到本页看总分与市场状态。

Sheet 1_Macro_Liquidity
A1: 宏观流动性（美联储与点阵图）
A2: 输入每次FOMC更新后的关键数字；用“评分”给宏观方向打分（+1/0/-1）。
A3: 更新日期（本行） | B3: 2026-02-10
A5: 指标 | B5: 最新值(输入) | C5: 上次值(输入) | D5: 变化(公式) | E5: 阈值/参考(输入) | F5: 评分(公式) | G5: 解读/备注 | H5: 数据来源(可选)
A6: 2026年末点阵图中值(%) | D6: =IF(OR(B6="",C6=""),"",B6-C6) | E6: 下降→偏鸽 | F6: =IF(B6="","",IF(D6<0,1,IF(D6>0,-1,0))) | G6: 关注“降到哪”而非“降多少”
A7: 长期中性利率(%) | D7: =IF(OR(B7="",C7=""),"",B7-C7) | E7: 锚点 | F7: =IF(B7="","",IF(D7>0,-1,IF(D7<0,1,0))) | G7: 中性利率若上修→估值中枢下移风险
A8: 预计不降息官员数 | D8: =IF(OR(B8="",C8=""),"",B8-C8) | E8: 分歧 | F8: =IF(B8="","",IF(D8>0,-1,IF(D8<0,1,0))) | G8: 人数上升→政策不确定性↑
A9: 主席更替/政策不确定性(0-2) | D9: =IF(OR(B9="",C9=""),"",B9-C9) | E9: 0低 1中 2高 | F9: =IF(B9="","",IF(B9>=2,-1,IF(B9=1,0,1))) | G9: 换届年可上调风险折价
G11: 宏观政策得分（合计） | H11: =SUM(F6:F9)

Sheet 2_RealRate_Valuation
A1: 实际利率与估值（Real Rate）
A2: 输入10Y TIPS（实际利率）与指数表现，用阈值判断成长股估值环境。
A3: 分母端压力： 当 TIPS $> 1.5\%$ 时，折现率（Discount Rate）明显上升，意味着同样的利润，在今天值更少的钱。估值约束： 历史经验表明，当 10 年期 TIPS 每上升 50 个基点（0.5%），在盈利预期不变的情况下，标普 500 的理论市盈率（P/E）会面临 5%-10% 的修正压力。2026 年现状： 目前 TIPS 在 1.8% - 2.0% 附近震荡，属于**“紧缩区间”的边缘**。这意味着目前美股的上涨完全是由“业绩增长（E）”拉动的，而非“估值扩张（P/E）”。
A5: 日期 | B5: 10Y TIPS(%) 输入 | C5: 1M前 输入 | D5: 变化(公式) | E5: 阈值上限(%) 输入 | F5: 评分(公式) | G5: 备注 | H5: 来源
A6: =INDEX(pq_tips_dfii10!$A:$A,COUNT(pq_tips_dfii10!$A:$A)-34+ROW()) | B6: =VLOOKUP(A6,查询1[],2,FALSE) | C6: =VLOOKUP(I6,查询1[],2,FALSE) | D6: =IF(OR(B6="",C6=""),"",B6-C6) | E6: 1.5 | F6: =IF(B6="","",IF(B6<=E6,1,IF(B6<=E6+0.25,0,-1))) | I6: =[1]!TDaysOffset(A6,"Period=M","Offset=-1")
A7: =INDEX(pq_tips_dfii10!$A:$A,COUNT(pq_tips_dfii10!$A:$A)-34+ROW()) | B7: =VLOOKUP(A7,查询1[],2,FALSE) | C7: =VLOOKUP(I7,查询1[],2,FALSE) | D7: =IF(OR(B7="",C7=""),"",B7-C7) | E7: 1.5 | F7: =IF(B7="","",IF(B7<=E7,1,IF(B7<=E7+0.25,0,-1))) | I7: =[1]!TDaysOffset(A7,"Period=M","Offset=-1")
A8: =INDEX(pq_tips_dfii10!$A:$A,COUNT(pq_tips_dfii10!$A:$A)-34+ROW()) | B8: =VLOOKUP(A8,查询1[],2,FALSE) | C8: =VLOOKUP(I8,查询1[],2,FALSE) | D8: =IF(OR(B8="",C8=""),"",B8-C8) | E8: 1.5 | F8: =IF(B8="","",IF(B8<=E8,1,IF(B8<=E8+0.25,0,-1))) | I8: =[1]!TDaysOffset(A8,"Period=M","Offset=-1")
A9: =INDEX(pq_tips_dfii10!$A:$A,COUNT(pq_tips_dfii10!$A:$A)-34+ROW()) | B9: =VLOOKUP(A9,查询1[],2,FALSE) | C9: =VLOOKUP(I9,查询1[],2,FALSE) | D9: =IF(OR(B9="",C9=""),"",B9-C9) | E9: 1.5 | F9: =IF(B9="","",IF(B9<=E9,1,IF(B9<=E9+0.25,0,-1))) | I9: =[1]!TDaysOffset(A9,"Period=M","Offset=-1")
A10: =INDEX(pq_tips_dfii10!$A:$A,COUNT(pq_tips_dfii10!$A:$A)-34+ROW()) | B10: =VLOOKUP(A10,查询1[],2,FALSE) | C10: =VLOOKUP(I10,查询1[],2,FALSE) | D10: =IF(OR(B10="",C10=""),"",B10-C10) | E10: 1.5 | F10: =IF(B10="","",IF(B10<=E10,1,IF(B10<=E10+0.25,0,-1))) | I10: =[1]!TDaysOffset(A10,"Period=M","Offset=-1")
A11: =INDEX(pq_tips_dfii10!$A:$A,COUNT(pq_tips_dfii10!$A:$A)-34+ROW()) | B11: =VLOOKUP(A11,查询1[],2,FALSE) | C11: =VLOOKUP(I11,查询1[],2,FALSE) | D11: =IF(OR(B11="",C11=""),"",B11-C11) | E11: 1.5 | F11: =IF(B11="","",IF(B11<=E11,1,IF(B11<=E11+0.25,0,-1))) | I11: =[1]!TDaysOffset(A11,"Period=M","Offset=-1")
A12: =INDEX(pq_tips_dfii10!$A:$A,COUNT(pq_tips_dfii10!$A:$A)-34+ROW()) | B12: =VLOOKUP(A12,查询1[],2,FALSE) | C12: =VLOOKUP(I12,查询1[],2,FALSE) | D12: =IF(OR(B12="",C12=""),"",B12-C12) | E12: 1.5 | F12: =IF(B12="","",IF(B12<=E12,1,IF(B12<=E12+0.25,0,-1))) | I12: =[1]!TDaysOffset(A12,"Period=M","Offset=-1")
A13: =INDEX(pq_tips_dfii10!$A:$A,COUNT(pq_tips_dfii10!$A:$A)-34+ROW()) | B13: =VLOOKUP(A13,查询1[],2,FALSE) | C13: =VLOOKUP(I13,查询1[],2,FALSE) | D13: =IF(OR(B13="",C13=""),"",B13-C13) | E13: 1.5 | F13: =IF(B13="","",IF(B13<=E13,1,IF(B13<=E13+0.25,0,-1))) | I13: =[1]!TDaysOffset(A13,"Period=M","Offset=-1")
A14: =INDEX(pq_tips_dfii10!$A:$A,COUNT(pq_tips_dfii10!$A:$A)-34+ROW()) | B14: =VLOOKUP(A14,查询1[],2,FALSE) | C14: =VLOOKUP(I14,查询1[],2,FALSE) | D14: =IF(OR(B14="",C14=""),"",B14-C14) | E14: 1.5 | F14: =IF(B14="","",IF(B14<=E14,1,IF(B14<=E14+0.25,0,-1))) | I14: =[1]!TDaysOffset(A14,"Period=M","Offset=-1")
A15: =INDEX(pq_tips_dfii10!$A:$A,COUNT(pq_tips_dfii10!$A:$A)-34+ROW()) | B15: =VLOOKUP(A15,查询1[],2,FALSE) | C15: =VLOOKUP(I15,查询1[],2,FALSE) | D15: =IF(OR(B15="",C15=""),"",B15-C15) | E15: 1.5 | F15: =IF(B15="","",IF(B15<=E15,1,IF(B15<=E15+0.25,0,-1))) | I15: =[1]!TDaysOffset(A15,"Period=M","Offset=-1")
A16: =INDEX(pq_tips_dfii10!$A:$A,COUNT(pq_tips_dfii10!$A:$A)-34+ROW()) | B16: =VLOOKUP(A16,查询1[],2,FALSE) | C16: =VLOOKUP(I16,查询1[],2,FALSE) | D16: =IF(OR(B16="",C16=""),"",B16-C16) | E16: 1.5 | F16: =IF(B16="","",IF(B16<=E16,1,IF(B16<=E16+0.25,0,-1))) | I16: =[1]!TDaysOffset(A16,"Period=M","Offset=-1")
A17: =INDEX(pq_tips_dfii10!$A:$A,COUNT(pq_tips_dfii10!$A:$A)-34+ROW()) | B17: =VLOOKUP(A17,查询1[],2,FALSE) | C17: =VLOOKUP(I17,查询1[],2,FALSE) | D17: =IF(OR(B17="",C17=""),"",B17-C17) | E17: 1.5 | F17: =IF(B17="","",IF(B17<=E17,1,IF(B17<=E17+0.25,0,-1))) | I17: =[1]!TDaysOffset(A17,"Period=M","Offset=-1")
... A35: =INDEX(pq_tips_dfii10!$A:$A,COUNT(pq_tips_dfii10!$A:$A)-34+ROW()) | B35: =VLOOKUP(A35,查询1[],2,FALSE) | C35: =VLOOKUP(I35,查询1[],2,FALSE) | D35: =IF(OR(B35="",C35=""),"",B35-C35) | E35: 1.5 | F35: =IF(B35="","",IF(B35<=E35,1,IF(B35<=E35+0.25,0,-1))) | I35: =[1]!TDaysOffset(A35,"Period=M","Offset=-1")
A37: 实际利率得分（最近一行） | B37: =IFERROR(LOOKUP(2,1/(F6:F35<>""),F6:F35),"")

Sheet 3_TGA_RRP
A1: TGA 与 RRP（财政流动性）
A2: TGA下降=释放流动性；RRP见底时“弹性”通常更大。
A5: 日期 | B5: TGA(亿美元) 输入 | C5: 上期TGA 输入 | D5: TGA变化(公式) | E5: 目标余额(亿美元) 输入 | F5: 评分(公式) | G5: 备注 | H5: 来源
A6: =INDEX(pq_tga_wtregen!$A:$A,COUNT(pq_tga_wtregen!$A:$A)-34+ROW()) | B6: =VLOOKUP(A6,pq_tga_wtregen!$A:$B,2,FALSE) | D6: =IF(OR(B6="",C6=""),"",B6-C6) | E6: 8500 | F6: =IF(B6="","",IF(B6<=E6,1,IF(B6<=E6+300,0,-1)))
A7: =INDEX(pq_tga_wtregen!$A:$A,COUNT(pq_tga_wtregen!$A:$A)-34+ROW()) | B7: =VLOOKUP(A7,pq_tga_wtregen!$A:$B,2,FALSE) | D7: =IF(OR(B7="",C7=""),"",B7-C7) | E7: 8500 | F7: =IF(B7="","",IF(B7<=E7,1,IF(B7<=E7+300,0,-1)))
A8: =INDEX(pq_tga_wtregen!$A:$A,COUNT(pq_tga_wtregen!$A:$A)-34+ROW()) | B8: =VLOOKUP(A8,pq_tga_wtregen!$A:$B,2,FALSE) | D8: =IF(OR(B8="",C8=""),"",B8-C8) | E8: 8500 | F8: =IF(B8="","",IF(B8<=E8,1,IF(B8<=E8+300,0,-1)))
A9: =INDEX(pq_tga_wtregen!$A:$A,COUNT(pq_tga_wtregen!$A:$A)-34+ROW()) | B9: =VLOOKUP(A9,pq_tga_wtregen!$A:$B,2,FALSE) | D9: =IF(OR(B9="",C9=""),"",B9-C9) | E9: 8500 | F9: =IF(B9="","",IF(B9<=E9,1,IF(B9<=E9+300,0,-1)))
A10: =INDEX(pq_tga_wtregen!$A:$A,COUNT(pq_tga_wtregen!$A:$A)-34+ROW()) | B10: =VLOOKUP(A10,pq_tga_wtregen!$A:$B,2,FALSE) | D10: =IF(OR(B10="",C10=""),"",B10-C10) | E10: 8500 | F10: =IF(B10="","",IF(B10<=E10,1,IF(B10<=E10+300,0,-1)))
A11: =INDEX(pq_tga_wtregen!$A:$A,COUNT(pq_tga_wtregen!$A:$A)-34+ROW()) | B11: =VLOOKUP(A11,pq_tga_wtregen!$A:$B,2,FALSE) | D11: =IF(OR(B11="",C11=""),"",B11-C11) | E11: 8500 | F11: =IF(B11="","",IF(B11<=E11,1,IF(B11<=E11+300,0,-1)))
A12: =INDEX(pq_tga_wtregen!$A:$A,COUNT(pq_tga_wtregen!$A:$A)-34+ROW()) | B12: =VLOOKUP(A12,pq_tga_wtregen!$A:$B,2,FALSE) | D12: =IF(OR(B12="",C12=""),"",B12-C12) | E12: 8500 | F12: =IF(B12="","",IF(B12<=E12,1,IF(B12<=E12+300,0,-1)))
A13: =INDEX(pq_tga_wtregen!$A:$A,COUNT(pq_tga_wtregen!$A:$A)-34+ROW()) | B13: =VLOOKUP(A13,pq_tga_wtregen!$A:$B,2,FALSE) | D13: =IF(OR(B13="",C13=""),"",B13-C13) | E13: 8500 | F13: =IF(B13="","",IF(B13<=E13,1,IF(B13<=E13+300,0,-1)))
A14: =INDEX(pq_tga_wtregen!$A:$A,COUNT(pq_tga_wtregen!$A:$A)-34+ROW()) | B14: =VLOOKUP(A14,pq_tga_wtregen!$A:$B,2,FALSE) | D14: =IF(OR(B14="",C14=""),"",B14-C14) | E14: 8500 | F14: =IF(B14="","",IF(B14<=E14,1,IF(B14<=E14+300,0,-1)))
A15: =INDEX(pq_tga_wtregen!$A:$A,COUNT(pq_tga_wtregen!$A:$A)-34+ROW()) | B15: =VLOOKUP(A15,pq_tga_wtregen!$A:$B,2,FALSE) | D15: =IF(OR(B15="",C15=""),"",B15-C15) | E15: 8500 | F15: =IF(B15="","",IF(B15<=E15,1,IF(B15<=E15+300,0,-1)))
A16: =INDEX(pq_tga_wtregen!$A:$A,COUNT(pq_tga_wtregen!$A:$A)-34+ROW()) | B16: =VLOOKUP(A16,pq_tga_wtregen!$A:$B,2,FALSE) | D16: =IF(OR(B16="",C16=""),"",B16-C16) | E16: 8500 | F16: =IF(B16="","",IF(B16<=E16,1,IF(B16<=E16+300,0,-1)))
A17: =INDEX(pq_tga_wtregen!$A:$A,COUNT(pq_tga_wtregen!$A:$A)-34+ROW()) | B17: =VLOOKUP(A17,pq_tga_wtregen!$A:$B,2,FALSE) | D17: =IF(OR(B17="",C17=""),"",B17-C17) | E17: 8500 | F17: =IF(B17="","",IF(B17<=E17,1,IF(B17<=E17+300,0,-1)))
... A35: =INDEX(pq_tga_wtregen!$A:$A,COUNT(pq_tga_wtregen!$A:$A)-34+ROW()) | B35: =VLOOKUP(A35,pq_tga_wtregen!$A:$B,2,FALSE) | D35: =IF(OR(B35="",C35=""),"",B35-C35) | E35: 8500 | F35: =IF(B35="","",IF(B35<=E35,1,IF(B35<=E35+300,0,-1)))
A37: RRP监控（可选）
A38: 日期 | B38: RRP(亿美元) 输入 | C38: 上期RRP 输入 | D38: RRP变化(公式) | E38: “见底”阈值(亿美元) 输入 | F38: 评分(公式) | G38: 备注 | H38: 来源
A39: =INDEX(pq_rrp_rrpontsyd!$A:$A,COUNT(pq_rrp_rrpontsyd!$A:$A)-20+ROW()-37) | B39: =VLOOKUP(A39,查询3[#All],2,FALSE) | D39: =IF(OR(B39="",C39=""),"",B39-C39) | E39: 1000 | F39: =IF(B39="","",IF(B39<=E39,1,0))
A40: =INDEX(pq_rrp_rrpontsyd!$A:$A,COUNT(pq_rrp_rrpontsyd!$A:$A)-20+ROW()-37) | B40: =VLOOKUP(A40,查询3[#All],2,FALSE) | D40: =IF(OR(B40="",C40=""),"",B40-C40) | E40: 1000 | F40: =IF(B40="","",IF(B40<=E40,1,0))
A41: =INDEX(pq_rrp_rrpontsyd!$A:$A,COUNT(pq_rrp_rrpontsyd!$A:$A)-20+ROW()-37) | B41: =VLOOKUP(A41,查询3[#All],2,FALSE) | D41: =IF(OR(B41="",C41=""),"",B41-C41) | E41: 1000 | F41: =IF(B41="","",IF(B41<=E41,1,0))
A42: =INDEX(pq_rrp_rrpontsyd!$A:$A,COUNT(pq_rrp_rrpontsyd!$A:$A)-20+ROW()-37) | B42: =VLOOKUP(A42,查询3[#All],2,FALSE) | D42: =IF(OR(B42="",C42=""),"",B42-C42) | E42: 1000 | F42: =IF(B42="","",IF(B42<=E42,1,0))
A43: =INDEX(pq_rrp_rrpontsyd!$A:$A,COUNT(pq_rrp_rrpontsyd!$A:$A)-20+ROW()-37) | B43: =VLOOKUP(A43,查询3[#All],2,FALSE) | D43: =IF(OR(B43="",C43=""),"",B43-C43) | E43: 1000 | F43: =IF(B43="","",IF(B43<=E43,1,0))
A44: =INDEX(pq_rrp_rrpontsyd!$A:$A,COUNT(pq_rrp_rrpontsyd!$A:$A)-20+ROW()-37) | B44: =VLOOKUP(A44,查询3[#All],2,FALSE) | D44: =IF(OR(B44="",C44=""),"",B44-C44) | E44: 1000 | F44: =IF(B44="","",IF(B44<=E44,1,0))
A45: =INDEX(pq_rrp_rrpontsyd!$A:$A,COUNT(pq_rrp_rrpontsyd!$A:$A)-20+ROW()-37) | B45: =VLOOKUP(A45,查询3[#All],2,FALSE) | D45: =IF(OR(B45="",C45=""),"",B45-C45) | E45: 1000 | F45: =IF(B45="","",IF(B45<=E45,1,0))
A46: =INDEX(pq_rrp_rrpontsyd!$A:$A,COUNT(pq_rrp_rrpontsyd!$A:$A)-20+ROW()-37) | B46: =VLOOKUP(A46,查询3[#All],2,FALSE) | D46: =IF(OR(B46="",C46=""),"",B46-C46) | E46: 1000 | F46: =IF(B46="","",IF(B46<=E46,1,0))
A47: =INDEX(pq_rrp_rrpontsyd!$A:$A,COUNT(pq_rrp_rrpontsyd!$A:$A)-20+ROW()-37) | B47: =VLOOKUP(A47,查询3[#All],2,FALSE) | D47: =IF(OR(B47="",C47=""),"",B47-C47) | E47: 1000 | F47: =IF(B47="","",IF(B47<=E47,1,0))
A48: =INDEX(pq_rrp_rrpontsyd!$A:$A,COUNT(pq_rrp_rrpontsyd!$A:$A)-20+ROW()-37) | B48: =VLOOKUP(A48,查询3[#All],2,FALSE) | D48: =IF(OR(B48="",C48=""),"",B48-C48) | E48: 1000 | F48: =IF(B48="","",IF(B48<=E48,1,0))
A49: =INDEX(pq_rrp_rrpontsyd!$A:$A,COUNT(pq_rrp_rrpontsyd!$A:$A)-20+ROW()-37) | B49: =VLOOKUP(A49,查询3[#All],2,FALSE) | D49: =IF(OR(B49="",C49=""),"",B49-C49) | E49: 1000 | F49: =IF(B49="","",IF(B49<=E49,1,0))
A50: =INDEX(pq_rrp_rrpontsyd!$A:$A,COUNT(pq_rrp_rrpontsyd!$A:$A)-20+ROW()-37) | B50: =VLOOKUP(A50,查询3[#All],2,FALSE) | D50: =IF(OR(B50="",C50=""),"",B50-C50) | E50: 1000 | F50: =IF(B50="","",IF(B50<=E50,1,0))
... A58: =INDEX(pq_rrp_rrpontsyd!$A:$A,COUNT(pq_rrp_rrpontsyd!$A:$A)-20+ROW()-37) | B58: =VLOOKUP(A58,查询3[#All],2,FALSE) | D58: =IF(OR(B58="",C58=""),"",B58-C58) | E58: 1000 | F58: =IF(B58="","",IF(B58<=E58,1,0))

Sheet 4_Micro_Fundamentals
A1: 微观基本面（Mag 7）
A2: 每季财报后更新：EPS增速、AI占比、CapEx强度、利润率、FCF。用红线规则识别风险。
A3: 提示：成本增速 > 营收增速通常触发“杀估值”；利润率( Margin )指引更关键。
A5: Ticker | B5: 公司 | C5: EPS YoY(%) 输入 | D5: 预期EPS(%) 输入 | E5: Surprise(公式) | F5: AI收入占比(%) 输入 | G5: CapEx/Rev(%) 输入 | H5: Margin QoQ(pp) 输入 | I5: FCF YoY(%) 输入
A6: AAPL | B6: Apple | C6: =IFERROR(((IFERROR(INDEX(pq_fh_earnings!$C:$C,MATCH($A6&"|1",pq_fh_earnings!$G:$G,0)),""))-(IFERROR(INDEX(pq_fh_earnings!$C:$C,MATCH($A6&"|5",pq_fh_earnings!$G:$G,0)),"")))/ABS(IFERROR(INDEX(pq_fh_earnings!$C:$C,MATCH($A6&"|5",pq_fh_earnings!$G:$G,0)),""))*100,"") | D6: =IFERROR(INDEX(pq_fh_earnings!$D:$D,MATCH($A6&"|1",pq_fh_earnings!$G:$G,0)),"") | E6: =IFERROR((INDEX(pq_fh_earnings!$C:$C,MATCH($A6&"|1",pq_fh_earnings!$G:$G,0))-INDEX(pq_fh_earnings!$D:$D,MATCH($A6&"|1",pq_fh_earnings!$G:$G,0)))/ABS(INDEX(pq_fh_earnings!$D:$D,MATCH($A6&"|1",pq_fh_earnings!$G:$G,0)))*100,"") | G6: =IFERROR(INDEX(pq_fh_financials!$D:$D,MATCH($A6&"|1",pq_fh_financials!$H:$H,0))/INDEX(pq_fh_financials!$C:$C,MATCH($A6&"|1",pq_fh_financials!$H:$H,0))*100,"") | H6: =IFERROR(INDEX(pq_fh_financials!$F:$F,MATCH($A6&"|1",pq_fh_financials!$H:$H,0))-INDEX(pq_fh_financials!$F:$F,MATCH($A6&"|2",pq_fh_financials!$H:$H,0)),"") | I6: =IFERROR((INDEX(pq_fh_financials!$E:$E,MATCH($A6&"|1",pq_fh_financials!$H:$H,0))-INDEX(pq_fh_financials!$E:$E,MATCH($A6&"|5",pq_fh_financials!$H:$H,0)))/ABS(INDEX(pq_fh_financials!$E:$E,MATCH($A6&"|5",pq_fh_financials!$H:$H,0)))*100,"")
A7: MSFT | B7: Microsoft | C7: =IFERROR(((IFERROR(INDEX(pq_fh_earnings!$C:$C,MATCH($A7&"|1",pq_fh_earnings!$G:$G,0)),""))-(IFERROR(INDEX(pq_fh_earnings!$C:$C,MATCH($A7&"|5",pq_fh_earnings!$G:$G,0)),"")))/ABS(IFERROR(INDEX(pq_fh_earnings!$C:$C,MATCH($A7&"|5",pq_fh_earnings!$G:$G,0)),""))*100,"") | D7: =IFERROR(INDEX(pq_fh_earnings!$D:$D,MATCH($A7&"|1",pq_fh_earnings!$G:$G,0)),"") | E7: =IFERROR((INDEX(pq_fh_earnings!$C:$C,MATCH($A7&"|1",pq_fh_earnings!$G:$G,0))-INDEX(pq_fh_earnings!$D:$D,MATCH($A7&"|1",pq_fh_earnings!$G:$G,0)))/ABS(INDEX(pq_fh_earnings!$D:$D,MATCH($A7&"|1",pq_fh_earnings!$G:$G,0)))*100,"") | G7: =IFERROR(INDEX(pq_fh_financials!$D:$D,MATCH($A7&"|1",pq_fh_financials!$H:$H,0))/INDEX(pq_fh_financials!$C:$C,MATCH($A7&"|1",pq_fh_financials!$H:$H,0))*100,"") | H7: =IFERROR(INDEX(pq_fh_financials!$F:$F,MATCH($A7&"|1",pq_fh_financials!$H:$H,0))-INDEX(pq_fh_financials!$F:$F,MATCH($A7&"|2",pq_fh_financials!$H:$H,0)),"") | I7: =IFERROR((INDEX(pq_fh_financials!$E:$E,MATCH($A7&"|1",pq_fh_financials!$H:$H,0))-INDEX(pq_fh_financials!$E:$E,MATCH($A7&"|5",pq_fh_financials!$H:$H,0)))/ABS(INDEX(pq_fh_financials!$E:$E,MATCH($A7&"|5",pq_fh_financials!$H:$H,0)))*100,"")
A8: NVDA | B8: NVIDIA | C8: =IFERROR(((IFERROR(INDEX(pq_fh_earnings!$C:$C,MATCH($A8&"|1",pq_fh_earnings!$G:$G,0)),""))-(IFERROR(INDEX(pq_fh_earnings!$C:$C,MATCH($A8&"|5",pq_fh_earnings!$G:$G,0)),"")))/ABS(IFERROR(INDEX(pq_fh_earnings!$C:$C,MATCH($A8&"|5",pq_fh_earnings!$G:$G,0)),""))*100,"") | D8: =IFERROR(INDEX(pq_fh_earnings!$D:$D,MATCH($A8&"|1",pq_fh_earnings!$G:$G,0)),"") | E8: =IFERROR((INDEX(pq_fh_earnings!$C:$C,MATCH($A8&"|1",pq_fh_earnings!$G:$G,0))-INDEX(pq_fh_earnings!$D:$D,MATCH($A8&"|1",pq_fh_earnings!$G:$G,0)))/ABS(INDEX(pq_fh_earnings!$D:$D,MATCH($A8&"|1",pq_fh_earnings!$G:$G,0)))*100,"") | G8: =IFERROR(INDEX(pq_fh_financials!$D:$D,MATCH($A8&"|1",pq_fh_financials!$H:$H,0))/INDEX(pq_fh_financials!$C:$C,MATCH($A8&"|1",pq_fh_financials!$H:$H,0))*100,"") | H8: =IFERROR(INDEX(pq_fh_financials!$F:$F,MATCH($A8&"|1",pq_fh_financials!$H:$H,0))-INDEX(pq_fh_financials!$F:$F,MATCH($A8&"|2",pq_fh_financials!$H:$H,0)),"") | I8: =IFERROR((INDEX(pq_fh_financials!$E:$E,MATCH($A8&"|1",pq_fh_financials!$H:$H,0))-INDEX(pq_fh_financials!$E:$E,MATCH($A8&"|5",pq_fh_financials!$H:$H,0)))/ABS(INDEX(pq_fh_financials!$E:$E,MATCH($A8&"|5",pq_fh_financials!$H:$H,0)))*100,"")
A9: GOOGL | B9: Alphabet | C9: =IFERROR(((IFERROR(INDEX(pq_fh_earnings!$C:$C,MATCH($A9&"|1",pq_fh_earnings!$G:$G,0)),""))-(IFERROR(INDEX(pq_fh_earnings!$C:$C,MATCH($A9&"|5",pq_fh_earnings!$G:$G,0)),"")))/ABS(IFERROR(INDEX(pq_fh_earnings!$C:$C,MATCH($A9&"|5",pq_fh_earnings!$G:$G,0)),""))*100,"") | D9: =IFERROR(INDEX(pq_fh_earnings!$D:$D,MATCH($A9&"|1",pq_fh_earnings!$G:$G,0)),"") | E9: =IFERROR((INDEX(pq_fh_earnings!$C:$C,MATCH($A9&"|1",pq_fh_earnings!$G:$G,0))-INDEX(pq_fh_earnings!$D:$D,MATCH($A9&"|1",pq_fh_earnings!$G:$G,0)))/ABS(INDEX(pq_fh_earnings!$D:$D,MATCH($A9&"|1",pq_fh_earnings!$G:$G,0)))*100,"") | G9: =IFERROR(INDEX(pq_fh_financials!$D:$D,MATCH($A9&"|1",pq_fh_financials!$H:$H,0))/INDEX(pq_fh_financials!$C:$C,MATCH($A9&"|1",pq_fh_financials!$H:$H,0))*100,"") | H9: =IFERROR(INDEX(pq_fh_financials!$F:$F,MATCH($A9&"|1",pq_fh_financials!$H:$H,0))-INDEX(pq_fh_financials!$F:$F,MATCH($A9&"|2",pq_fh_financials!$H:$H,0)),"") | I9: =IFERROR((INDEX(pq_fh_financials!$E:$E,MATCH($A9&"|1",pq_fh_financials!$H:$H,0))-INDEX(pq_fh_financials!$E:$E,MATCH($A9&"|5",pq_fh_financials!$H:$H,0)))/ABS(INDEX(pq_fh_financials!$E:$E,MATCH($A9&"|5",pq_fh_financials!$H:$H,0)))*100,"")
A10: AMZN | B10: Amazon | C10: =IFERROR(((IFERROR(INDEX(pq_fh_earnings!$C:$C,MATCH($A10&"|1",pq_fh_earnings!$G:$G,0)),""))-(IFERROR(INDEX(pq_fh_earnings!$C:$C,MATCH($A10&"|5",pq_fh_earnings!$G:$G,0)),"")))/ABS(IFERROR(INDEX(pq_fh_earnings!$C:$C,MATCH($A10&"|5",pq_fh_earnings!$G:$G,0)),""))*100,"") | D10: =IFERROR(INDEX(pq_fh_earnings!$D:$D,MATCH($A10&"|1",pq_fh_earnings!$G:$G,0)),"") | E10: =IFERROR((INDEX(pq_fh_earnings!$C:$C,MATCH($A10&"|1",pq_fh_earnings!$G:$G,0))-INDEX(pq_fh_earnings!$D:$D,MATCH($A10&"|1",pq_fh_earnings!$G:$G,0)))/ABS(INDEX(pq_fh_earnings!$D:$D,MATCH($A10&"|1",pq_fh_earnings!$G:$G,0)))*100,"") | G10: =IFERROR(INDEX(pq_fh_financials!$D:$D,MATCH($A10&"|1",pq_fh_financials!$H:$H,0))/INDEX(pq_fh_financials!$C:$C,MATCH($A10&"|1",pq_fh_financials!$H:$H,0))*100,"") | H10: =IFERROR(INDEX(pq_fh_financials!$F:$F,MATCH($A10&"|1",pq_fh_financials!$H:$H,0))-INDEX(pq_fh_financials!$F:$F,MATCH($A10&"|2",pq_fh_financials!$H:$H,0)),"") | I10: =IFERROR((INDEX(pq_fh_financials!$E:$E,MATCH($A10&"|1",pq_fh_financials!$H:$H,0))-INDEX(pq_fh_financials!$E:$E,MATCH($A10&"|5",pq_fh_financials!$H:$H,0)))/ABS(INDEX(pq_fh_financials!$E:$E,MATCH($A10&"|5",pq_fh_financials!$H:$H,0)))*100,"")
A11: META | B11: Meta | C11: =IFERROR(((IFERROR(INDEX(pq_fh_earnings!$C:$C,MATCH($A11&"|1",pq_fh_earnings!$G:$G,0)),""))-(IFERROR(INDEX(pq_fh_earnings!$C:$C,MATCH($A11&"|5",pq_fh_earnings!$G:$G,0)),"")))/ABS(IFERROR(INDEX(pq_fh_earnings!$C:$C,MATCH($A11&"|5",pq_fh_earnings!$G:$G,0)),""))*100,"") | D11: =IFERROR(INDEX(pq_fh_earnings!$D:$D,MATCH($A11&"|1",pq_fh_earnings!$G:$G,0)),"") | E11: =IFERROR((INDEX(pq_fh_earnings!$C:$C,MATCH($A11&"|1",pq_fh_earnings!$G:$G,0))-INDEX(pq_fh_earnings!$D:$D,MATCH($A11&"|1",pq_fh_earnings!$G:$G,0)))/ABS(INDEX(pq_fh_earnings!$D:$D,MATCH($A11&"|1",pq_fh_earnings!$G:$G,0)))*100,"") | G11: =IFERROR(INDEX(pq_fh_financials!$D:$D,MATCH($A11&"|1",pq_fh_financials!$H:$H,0))/INDEX(pq_fh_financials!$C:$C,MATCH($A11&"|1",pq_fh_financials!$H:$H,0))*100,"") | H11: =IFERROR(INDEX(pq_fh_financials!$F:$F,MATCH($A11&"|1",pq_fh_financials!$H:$H,0))-INDEX(pq_fh_financials!$F:$F,MATCH($A11&"|2",pq_fh_financials!$H:$H,0)),"") | I11: =IFERROR((INDEX(pq_fh_financials!$E:$E,MATCH($A11&"|1",pq_fh_financials!$H:$H,0))-INDEX(pq_fh_financials!$E:$E,MATCH($A11&"|5",pq_fh_financials!$H:$H,0)))/ABS(INDEX(pq_fh_financials!$E:$E,MATCH($A11&"|5",pq_fh_financials!$H:$H,0)))*100,"")
A12: TSLA | B12: Tesla | C12: =IFERROR(((IFERROR(INDEX(pq_fh_earnings!$C:$C,MATCH($A12&"|1",pq_fh_earnings!$G:$G,0)),""))-(IFERROR(INDEX(pq_fh_earnings!$C:$C,MATCH($A12&"|5",pq_fh_earnings!$G:$G,0)),"")))/ABS(IFERROR(INDEX(pq_fh_earnings!$C:$C,MATCH($A12&"|5",pq_fh_earnings!$G:$G,0)),""))*100,"") | D12: =IFERROR(INDEX(pq_fh_earnings!$D:$D,MATCH($A12&"|1",pq_fh_earnings!$G:$G,0)),"") | E12: =IFERROR((INDEX(pq_fh_earnings!$C:$C,MATCH($A12&"|1",pq_fh_earnings!$G:$G,0))-INDEX(pq_fh_earnings!$D:$D,MATCH($A12&"|1",pq_fh_earnings!$G:$G,0)))/ABS(INDEX(pq_fh_earnings!$D:$D,MATCH($A12&"|1",pq_fh_earnings!$G:$G,0)))*100,"") | G12: =IFERROR(INDEX(pq_fh_financials!$D:$D,MATCH($A12&"|1",pq_fh_financials!$H:$H,0))/INDEX(pq_fh_financials!$C:$C,MATCH($A12&"|1",pq_fh_financials!$H:$H,0))*100,"") | H12: =IFERROR(INDEX(pq_fh_financials!$F:$F,MATCH($A12&"|1",pq_fh_financials!$H:$H,0))-INDEX(pq_fh_financials!$F:$F,MATCH($A12&"|2",pq_fh_financials!$H:$H,0)),"") | I12: =IFERROR((INDEX(pq_fh_financials!$E:$E,MATCH($A12&"|1",pq_fh_financials!$H:$H,0))-INDEX(pq_fh_financials!$E:$E,MATCH($A12&"|5",pq_fh_financials!$H:$H,0)))/ABS(INDEX(pq_fh_financials!$E:$E,MATCH($A12&"|5",pq_fh_financials!$H:$H,0)))*100,"")
A15: Mag7综合得分（按“超预期+利润率+FCF”粗略打分，可自行改权重）
A16: Ticker | B16: Surprise | C16: Margin QoQ | D16: FCF YoY | E16: 单股得分(公式) | F16: 权重(输入) | G16: 加权得分(公式) | H16: 备注
A17: AAPL | B17: =E6 | C17: =H6 | D17: =I6 | E17: =IFERROR(SIGN((IF(B17>0,1,0)+IF(C17>0,1,0)+IF(D17>0,1,0))-1),"") | F17: 0.1429 | G17: =IF(OR(E17="",F17=""),"",E17*F17)
A18: MSFT | B18: =E7 | C18: =H7 | D18: =I7 | E18: =IFERROR(SIGN((IF(B18>0,1,0)+IF(C18>0,1,0)+IF(D18>0,1,0))-1),"") | F18: 0.1429 | G18: =IF(OR(E18="",F18=""),"",E18*F18)
A19: NVDA | B19: =E8 | C19: =H8 | D19: =I8 | E19: =IFERROR(SIGN((IF(B19>0,1,0)+IF(C19>0,1,0)+IF(D19>0,1,0))-1),"") | F19: 0.1429 | G19: =IF(OR(E19="",F19=""),"",E19*F19)
A20: GOOGL | B20: =E9 | C20: =H9 | D20: =I9 | E20: =IFERROR(SIGN((IF(B20>0,1,0)+IF(C20>0,1,0)+IF(D20>0,1,0))-1),"") | F20: 0.1429 | G20: =IF(OR(E20="",F20=""),"",E20*F20)
A21: AMZN | B21: =E10 | C21: =H10 | D21: =I10 | E21: =IFERROR(SIGN((IF(B21>0,1,0)+IF(C21>0,1,0)+IF(D21>0,1,0))-1),"") | F21: 0.1429 | G21: =IF(OR(E21="",F21=""),"",E21*F21)
A22: META | B22: =E11 | C22: =H11 | D22: =I11 | E22: =IFERROR(SIGN((IF(B22>0,1,0)+IF(C22>0,1,0)+IF(D22>0,1,0))-1),"") | F22: 0.1429 | G22: =IF(OR(E22="",F22=""),"",E22*F22)
A23: TSLA | B23: =E12 | C23: =H12 | D23: =I12 | E23: =IFERROR(SIGN((IF(B23>0,1,0)+IF(C23>0,1,0)+IF(D23>0,1,0))-1),"") | F23: 0.1429 | G23: =IF(OR(E23="",F23=""),"",E23*F23)
F24: 权重合计 | G24: =SUM(F17:F23)
F25: Mag7得分（加权） | G25: =SUM(G17:G23)

Sheet 5_Price_Action
A1: 价格行动（财报后反应）
A2: 记录“利好不涨 / 利空不跌”频率与板块联动性，用作牛熊转换最敏感信号。
A5: 日期 | B5: Ticker | C5: EPS结果 | D5: 指引结果 | E5: 开盘反应 | F5: 收盘反应 | G5: 类型(公式) | H5: 板块联动(0-1) 输入 | I5: 备注
G6: =IF(OR(C6="",F6=""),"",IF(AND(OR(C6="Beat",D6="上修"),OR(F6="回落",F6="收跌")),"利好不涨", IF(AND(OR(C6="Miss",D6="下修"),OR(F6="反弹",F6="震荡")),"利空不跌","正常")) )
G7: =IF(OR(C7="",F7=""),"",IF(AND(OR(C7="Beat",D7="上修"),OR(F7="回落",F7="收跌")),"利好不涨", IF(AND(OR(C7="Miss",D7="下修"),OR(F7="反弹",F7="震荡")),"利空不跌","正常")) )
G8: =IF(OR(C8="",F8=""),"",IF(AND(OR(C8="Beat",D8="上修"),OR(F8="回落",F8="收跌")),"利好不涨", IF(AND(OR(C8="Miss",D8="下修"),OR(F8="反弹",F8="震荡")),"利空不跌","正常")) )
G9: =IF(OR(C9="",F9=""),"",IF(AND(OR(C9="Beat",D9="上修"),OR(F9="回落",F9="收跌")),"利好不涨", IF(AND(OR(C9="Miss",D9="下修"),OR(F9="反弹",F9="震荡")),"利空不跌","正常")) )
G10: =IF(OR(C10="",F10=""),"",IF(AND(OR(C10="Beat",D10="上修"),OR(F10="回落",F10="收跌")),"利好不涨", IF(AND(OR(C10="Miss",D10="下修"),OR(F10="反弹",F10="震荡")),"利空不跌","正常")) )
G11: =IF(OR(C11="",F11=""),"",IF(AND(OR(C11="Beat",D11="上修"),OR(F11="回落",F11="收跌")),"利好不涨", IF(AND(OR(C11="Miss",D11="下修"),OR(F11="反弹",F11="震荡")),"利空不跌","正常")) )
G12: =IF(OR(C12="",F12=""),"",IF(AND(OR(C12="Beat",D12="上修"),OR(F12="回落",F12="收跌")),"利好不涨", IF(AND(OR(C12="Miss",D12="下修"),OR(F12="反弹",F12="震荡")),"利空不跌","正常")) )
G13: =IF(OR(C13="",F13=""),"",IF(AND(OR(C13="Beat",D13="上修"),OR(F13="回落",F13="收跌")),"利好不涨", IF(AND(OR(C13="Miss",D13="下修"),OR(F13="反弹",F13="震荡")),"利空不跌","正常")) )
G14: =IF(OR(C14="",F14=""),"",IF(AND(OR(C14="Beat",D14="上修"),OR(F14="回落",F14="收跌")),"利好不涨", IF(AND(OR(C14="Miss",D14="下修"),OR(F14="反弹",F14="震荡")),"利空不跌","正常")) )
G15: =IF(OR(C15="",F15=""),"",IF(AND(OR(C15="Beat",D15="上修"),OR(F15="回落",F15="收跌")),"利好不涨", IF(AND(OR(C15="Miss",D15="下修"),OR(F15="反弹",F15="震荡")),"利空不跌","正常")) )
G16: =IF(OR(C16="",F16=""),"",IF(AND(OR(C16="Beat",D16="上修"),OR(F16="回落",F16="收跌")),"利好不涨", IF(AND(OR(C16="Miss",D16="下修"),OR(F16="反弹",F16="震荡")),"利空不跌","正常")) )
G17: =IF(OR(C17="",F17=""),"",IF(AND(OR(C17="Beat",D17="上修"),OR(F17="回落",F17="收跌")),"利好不涨", IF(AND(OR(C17="Miss",D17="下修"),OR(F17="反弹",F17="震荡")),"利空不跌","正常")) )
... G85: =IF(OR(C85="",F85=""),"",IF(AND(OR(C85="Beat",D85="上修"),OR(F85="回落",F85="收跌")),"利好不涨", IF(AND(OR(C85="Miss",D85="下修"),OR(F85="反弹",F85="震荡")),"利空不跌","正常")) )
A88: 统计（最近80条记录）
A89: 利好不涨比例 | B89: =IFERROR(COUNTIF(G6:G85,"利好不涨")/COUNTIF(G6:G85,"<>"),"")
A90: 利空不跌比例 | B90: =IFERROR(COUNTIF(G6:G85,"利空不跌")/COUNTIF(G6:G85,"<>"),"")
A91: 板块联动均值 | B91: =IFERROR(AVERAGEIF(H6:H85,">=0"),"")

Sheet 6_Data_API_PowerQuery
A1: 数据接口字段占位（FRED / 财政部）— 便于 PowerQuery 自动抓取
A2: 更新时间：2026-02-10 | 说明：本页只提供“接口字段占位 + 建议查询参数”，便于你在 PowerQuery 里复制粘贴并映射到各Sheet。
A4: A) FRED（宏观利率/通胀预期/流动性代理）
A5: 目标字段 | B5: 来源 | C5: Series ID / 数据集 | D5: Endpoint 模板 | E5: 关键参数占位 | F5: PowerQuery 目标表名 | G5: 刷新频率建议 | H5: 日期字段 | I5: 数值字段 | J5: 备注
A6: 联邦基金利率 | B6: FRED | C6: DFF | D6: https://api.stlouisfed.org/fred/series/observations?series_id={SERIES_ID}&api_key={FRED_API_KEY}&file_type=json&observation_start={START_DATE}&observation_end={END_DATE}&frequency={FREQ} | E6: {FRED_API_KEY}; {START_DATE}; {END_DATE}; FREQ=d | F6: pq_fedfunds_dff | G6: 日/周 | H6: date | I6: value | J6: 用于验证点阵图与市场定价偏离
A7: 10Y TIPS 实际利率 | B7: FRED | C7: DFII10 | D7: https://api.stlouisfed.org/fred/series/observations?series_id={SERIES_ID}&api_key={FRED_API_KEY}&file_type=json&observation_start={START_DATE}&observation_end={END_DATE}&frequency={FREQ} | E7: {FRED_API_KEY}; {START_DATE}; {END_DATE}; FREQ=d | F7: pq_tips_dfii10 | G7: 日/周 | H7: date | I7: value | J7: 用于Sheet2：实际利率阈值(0.50–0.75%)
A8: 10Y 通胀预期（Breakeven） | B8: FRED | C8: T10YIE | D8: https://api.stlouisfed.org/fred/series/observations?series_id={SERIES_ID}&api_key={FRED_API_KEY}&file_type=json&observation_start={START_DATE}&observation_end={END_DATE}&frequency={FREQ} | E8: {FRED_API_KEY}; {START_DATE}; {END_DATE}; FREQ=d | F8: pq_breakeven_t10yie | G8: 日/周 | H8: date | I8: value | J8: 名义-实际的隐含通胀预期
A9: 财政部一般账户TGA（代理） | B9: FRED | C9: WTREGEN | D9: https://api.stlouisfed.org/fred/series/observations?series_id={SERIES_ID}&api_key={FRED_API_KEY}&file_type=json&observation_start={START_DATE}&observation_end={END_DATE}&frequency={FREQ} | E9: {FRED_API_KEY}; {START_DATE}; {END_DATE}; FREQ=w | F9: pq_tga_wtregen | G9: 周 | H9: date | I9: value | J9: 用于Sheet3：TGA监控（注意单位/口径）
A10: 隔夜逆回购 ON RRP | B10: FRED | C10: RRPONTSYD | D10: https://api.stlouisfed.org/fred/series/observations?series_id={SERIES_ID}&api_key={FRED_API_KEY}&file_type=json&observation_start={START_DATE}&observation_end={END_DATE}&frequency={FREQ} | E10: {FRED_API_KEY}; {START_DATE}; {END_DATE}; FREQ=d | F10: pq_rrp_rrpontsyd | G10: 日/周 | H10: date | I10: value | J10: 用于Sheet3：RRP见底信号
A13: B) 美国财政部 Fiscal Data API（财政部官网接口，用于TGA/现金收支等更细口径）
A14: 目标字段 | B14: 来源 | C14: 数据集 / 路径占位 | D14: Endpoint 模板 | E14: 关键参数占位 | F14: PowerQuery 目标表名 | G14: 刷新频率建议 | H14: 日期字段 | I14: 数值字段 | J14: 备注
A15: TGA 余额（官方口径） | B15: Treasury Fiscal Data | C15: {PATH} 例如: account_balances/operating_cash_balance | D15: https://api.fiscaldata.treasury.gov/services/api/fiscal_service/v2/{PATH}?filter={FILTER}&fields={FIELDS}&sort={SORT}&page[number]={PAGE_NO}&page[size]={PAGE_SIZE} | E15: {PATH}; FILTER=record_date:gte:{START_DATE},record_date:lte:{END_DATE}; FIELDS=record_date,open_today_bal; SORT=record_date | F15: pq_tga_treasury_official | G15: 日/周 | H15: record_date | I15: open_today_bal | J15: 不同数据集字段名可能略有差异：在PQ里先预览再改FIELDS
A16: 财政部现金收支（可选） | B16: Treasury Fiscal Data | C16: {PATH} 例如: federal_accounting/operating_cash_balance 或 DTS相关数据集 | D16: https://api.fiscaldata.treasury.gov/services/api/fiscal_service/v2/{PATH}?filter={FILTER}&fields={FIELDS}&sort={SORT}&page[number]={PAGE_NO}&page[size]={PAGE_SIZE} | E16: {PATH}; FILTER=...; FIELDS=...; SORT=... | F16: pq_treasury_cashflow_optional | G16: 周/月 | H16: record_date | I16: value | J16: 用于解释TGA变动背后：发债/支出节奏
A19: C) 映射到本模板各Sheet的建议（PowerQuery加载后“表→单元格”引用）
A20: 目标Sheet | B20: 字段映射 | C20: 建议做法
A21: Sheet2_RealRate_Valuation | B21: 10Y TIPS(%) ← pq_tips_dfii10[value]（按日期匹配/最新值） | C21: 把“最新值”写入B列；日期写入A列；可用PQ直接生成两列表后粘贴为值或连接表格。
A22: Sheet3_TGA_RRP | B22: TGA(亿美元) ← pq_tga_wtregen 或 pq_tga_treasury_official（注意单位换算） | C22: 建议在PQ里先把单位统一成“亿美元”，再加载到Sheet3。
A23: Sheet3_TGA_RRP | B23: RRP(亿美元) ← pq_rrp_rrpontsyd[value]（注意单位） | C23: RRP常以美元计，建议PQ里/1e8转换为亿美元。
A24: Sheet1_Macro_Liquidity | B24: 联邦基金利率 ← pq_fedfunds_dff[value]（辅助监控） | C24: 点阵图仍需要手动更新，但可用联邦基金利率校验“实际路径”。
A26: D) PowerQuery快速步骤（复制到你团队文档也行）
A27: 1) Excel → 数据(Data) → 获取数据(Get Data) → 从其他源(From Other Sources) → 空白查询(Blank Query) 2) 在高级编辑器(Advanced Editor)中粘贴 Web.Contents(...) 的URL（上面黄色单元格里的模板） 3) 解析 JSON：转为表 → 展开 data/observations → 选择 date/value 字段 4) 类型转换：date→日期，value→数字；必要时过滤 '.' 或空值 5) 单位统一：例如 RRP/TGA 换算为“亿美元” 6) 加载为表到工作簿：表名建议使用 pq_* 前缀 7) Dashboard 用链接引用这些表的最新值（LOOKUP/INDEX/MATCH）或直接在各Sheet把表“粘贴为值” 提示：FRED 需要 FRED_API_KEY；财政部 Fiscal Data API 一般不需要 Key。
A33: D) Finnhub 微观基本面（用于 Sheet4：4_Micro_Fundamentals）
A34: API Key（在 7_Config!B2 填入）
A35: Earnings Endpoint | C35: https://finnhub.io/api/v1/stock/earnings?symbol={SYMBOL}&token={FINNHUB_API_KEY}
A36: Financials Endpoint | C36: https://finnhub.io/api/v1/stock/financials-reported?symbol={SYMBOL}&token={FINNHUB_API_KEY}
A38: PowerQuery 目标表（把结果加载到这些Sheet）
A39: pq_fh_earnings | B39: 字段：symbol, period, actual_eps, estimate_eps, surprise_pct（按 symbol 升序 + period 降序排序）
A40: pq_fh_financials | B40: 字段：symbol, period, revenue, capex, free_cash_flow, net_profit_margin（按 symbol 升序 + period 降序排序）
A42: 注意：模板已在 Sheet4 用 INDEX/MATCH 自动取每个 ticker 的 Rank=1（最新）与 Rank=5（同比）数据。

Sheet pq_tips_dfii10
A1: date | B1: value
A2: 43832 | B2: 0.08
A3: 43833 | B3: 0.03
A4: 43836 | B4: 0.06
A5: 43837 | B5: 0.09
A6: 43838 | B6: 0.12
A7: 43839 | B7: 0.11
A8: 43840 | B8: 0.07
A9: 43843 | B9: 0.08
A10: 43844 | B10: 0.05
A11: 43845 | B11: 0.04
A12: 43846 | B12: 0.07
A13: 43847 | B13: 0.09
... A1526: 46059 | B1526: 1.88

Sheet pq_tga_wtregen
A1: date | B1: value
A2: 43831 | B2: 3825.53
A3: 43838 | B3: 3670.02
A4: 43845 | B4: 3509.87
A5: 43852 | B5: 4039.41
A6: 43859 | B6: 4320.61
A7: 43866 | B7: 4133.22
A8: 43873 | B8: 4112.37
A9: 43880 | B9: 4288.05
A10: 43887 | B10: 4393.65
A11: 43894 | B11: 3745.15
A12: 43901 | B12: 3805.56
A13: 43908 | B13: 3625.76
... A320: 46057 | B320: 9087.73

Sheet pq_rrp_rrpontsyd
A1: date | B1: value
A2: 43832 | B2: 3.1e-08
A3: 43833 | B3: 4.251e-08
A4: 43836 | B4: 3.825e-08
A5: 43837 | B5: 1.602e-08
A6: 43838 | B6: 8.76e-09
A7: 43839 | B7: 4.01e-09
A8: 43840 | B8: 6.27e-09
A9: 43843 | B9: 1e-08
A10: 43844 | B10: 6.56e-09
A11: 43845 | B11: 6.75e-09
A12: 43846 | B12: 3e-09
A13: 43847 | B13: 1.615e-07
... A1525: 46062 | B1525: 1.306e-08

Sheet tbl_mag7
A1: symbol

Sheet 7_Config
A1: API Keys / 参数配置
A2: Finnhub_API_Key | B2: d65ul8pr01qiish14p3gd65ul8pr01qiish14p40
A4: Tickers (Mag7)
A5: AAPL
A6: MSFT
A7: NVDA
A8: GOOGL
A9: AMZN
A10: META
A11: TSLA

Sheet pq_fh_earnings
A1: symbol | B1: period | C1: actual_eps | D1: estimate_eps | E1: surprise_pct | F1: rank | G1: key_sym_rank
F2: =IF(A2="","",COUNTIF($A$2:A2,A2)) | G2: =IF(A2="","",A2&"|"&F2)
F3: =IF(A3="","",COUNTIF($A$2:A3,A3)) | G3: =IF(A3="","",A3&"|"&F3)
F4: =IF(A4="","",COUNTIF($A$2:A4,A4)) | G4: =IF(A4="","",A4&"|"&F4)
F5: =IF(A5="","",COUNTIF($A$2:A5,A5)) | G5: =IF(A5="","",A5&"|"&F5)
F6: =IF(A6="","",COUNTIF($A$2:A6,A6)) | G6: =IF(A6="","",A6&"|"&F6)
F7: =IF(A7="","",COUNTIF($A$2:A7,A7)) | G7: =IF(A7="","",A7&"|"&F7)
F8: =IF(A8="","",COUNTIF($A$2:A8,A8)) | G8: =IF(A8="","",A8&"|"&F8)
F9: =IF(A9="","",COUNTIF($A$2:A9,A9)) | G9: =IF(A9="","",A9&"|"&F9)
F10: =IF(A10="","",COUNTIF($A$2:A10,A10)) | G10: =IF(A10="","",A10&"|"&F10)
F11: =IF(A11="","",COUNTIF($A$2:A11,A11)) | G11: =IF(A11="","",A11&"|"&F11)
F12: =IF(A12="","",COUNTIF($A$2:A12,A12)) | G12: =IF(A12="","",A12&"|"&F12)
F13: =IF(A13="","",COUNTIF($A$2:A13,A13)) | G13: =IF(A13="","",A13&"|"&F13)
... F501: =IF(A501="","",COUNTIF($A$2:A501,A501)) | G501: =IF(A501="","",A501&"|"&F501)

Sheet pq_fh_financials
A1: symbol | B1: period | C1: revenue | D1: capex | E1: free_cash_flow | F1: net_profit_margin | G1: rank | H1: key_sym_rank
G2: =IF(A2="","",COUNTIF($A$2:A2,A2)) | H2: =IF(A2="","",A2&"|"&G2)
G3: =IF(A3="","",COUNTIF($A$2:A3,A3)) | H3: =IF(A3="","",A3&"|"&G3)
G4: =IF(A4="","",COUNTIF($A$2:A4,A4)) | H4: =IF(A4="","",A4&"|"&G4)
G5: =IF(A5="","",COUNTIF($A$2:A5,A5)) | H5: =IF(A5="","",A5&"|"&G5)
G6: =IF(A6="","",COUNTIF($A$2:A6,A6)) | H6: =IF(A6="","",A6&"|"&G6)
G7: =IF(A7="","",COUNTIF($A$2:A7,A7)) | H7: =IF(A7="","",A7&"|"&G7)
G8: =IF(A8="","",COUNTIF($A$2:A8,A8)) | H8: =IF(A8="","",A8&"|"&G8)
G9: =IF(A9="","",COUNTIF($A$2:A9,A9)) | H9: =IF(A9="","",A9&"|"&G9)
G10: =IF(A10="","",COUNTIF($A$2:A10,A10)) | H10: =IF(A10="","",A10&"|"&G10)
G11: =IF(A11="","",COUNTIF($A$2:A11,A11)) | H11: =IF(A11="","",A11&"|"&G11)
G12: =IF(A12="","",COUNTIF($A$2:A12,A12)) | H12: =IF(A12="","",A12&"|"&G12)
G13: =IF(A13="","",COUNTIF($A$2:A13,A13)) | H13: =IF(A13="","",A13&"|"&G13)
... G501: =IF(A501="","",COUNTIF($A$2:A501,A501)) | H501: =IF(A501="","",A501&"|"&G501)
